LICENSE
README.md
setup.py
al4nlp/__init__.py
al4nlp/active_learner.py
al4nlp/active_selector.py
al4nlp/constructors/__init__.py
al4nlp/constructors/construct_active_learner.py
al4nlp/constructors/construct_wrapper.py
al4nlp/model_wrappers/__init__.py
al4nlp/model_wrappers/flair/__init__.py
al4nlp/model_wrappers/flair/flair_trainer.py
al4nlp/model_wrappers/flair/wrapper_flair.py
al4nlp/model_wrappers/pytorch/__init__.py
al4nlp/model_wrappers/pytorch/wrapper_cls_pytorch.py
al4nlp/model_wrappers/pytorch/wrapper_encoder_pytorch.py
al4nlp/model_wrappers/pytorch/wrapper_ner_pytorch.py
al4nlp/model_wrappers/transformers/__init__.py
al4nlp/model_wrappers/transformers/trainer_for_pseudo_labeled.py
al4nlp/model_wrappers/transformers/transformers_base_wrapper.py
al4nlp/model_wrappers/transformers/wrapper_cls.py
al4nlp/model_wrappers/transformers/wrapper_encoder.py
al4nlp/model_wrappers/transformers/wrapper_ner.py
al4nlp/models/__init__.py
al4nlp/models/bilstm_crf.py
al4nlp/models/fnet.py
al4nlp/models/ner_bilstm.py
al4nlp/models/text_classification_cnn.py
al4nlp/models/spectral_normalization/__init__.py
al4nlp/models/spectral_normalization/spectral_norm_conv_inplace.py
al4nlp/models/spectral_normalization/spectral_norm_fc.py
al4nlp/pool_subsampling_strategies/__init__.py
al4nlp/pool_subsampling_strategies/naive_subsampling.py
al4nlp/pool_subsampling_strategies/random_subsampling.py
al4nlp/pool_subsampling_strategies/ups_subsampling.py
al4nlp/query_strategies/__init__.py
al4nlp/query_strategies/actune_sampling.py
al4nlp/query_strategies/al_strategy.py
al4nlp/query_strategies/al_strategy_utils.py
al4nlp/query_strategies/alps_sampling.py
al4nlp/query_strategies/badge_sampling.py
al4nlp/query_strategies/bait_sampling.py
al4nlp/query_strategies/bald_sampling.py
al4nlp/query_strategies/batchbald_sampling.py
al4nlp/query_strategies/breaking_ties_sampling.py
al4nlp/query_strategies/cal_sampling.py
al4nlp/query_strategies/cluster_margin_sampling.py
tmpproject.egg-info/PKG-INFO
tmpproject.egg-info/SOURCES.txt
tmpproject.egg-info/dependency_links.txt
tmpproject.egg-info/requires.txt
tmpproject.egg-info/top_level.txt