Metadata-Version: 2.1
Name: tmpproject
Version: 0.0.3
Summary: A Library for active learning. Supports text classification and sequence tagging tasks.
Author: Tsvigun A., Sanochkin L., Kuzmin G., Larionov D., and Dr Shelmanov A.
License: MIT
Keywords: NLP active AL deep learning transformer pytorch PLASM UPS
License-File: LICENSE
